mwm/__init__.py
mwm/__main__.py
mwm/decode_id.py
mwm/dump_mwm.py
mwm/exceptions.py
mwm/feature_types.py
mwm/find_feature.py
mwm/ft2osm.py
mwm/mwm_feature_compare.py
mwm/mwm_interface.py
mwm/mwm_pygen.py
mwm/mwm_python.py
mwm/mwm_test.py
mwm/types.py
mwm/utils.py
omim_mwm-10.3.0rc2.dist-info/METADATA
omim_mwm-10.3.0rc2.dist-info/WHEEL
omim_mwm-10.3.0rc2.dist-info/top_level.txt
omim_mwm-10.3.0rc2.dist-info/RECORD
