Metadata-Version: 2.1
Name: omim-mwm
Version: 10.3.0rc2
Summary: This package is a library that can work with mwm files.
Home-page: https://github.com/mapsme
Author: My.com B.V. (Mail.Ru Group)
Author-email: dev@maps.me
License: UNKNOWN
Platform: UNKNOWN
Classifier: Programming Language :: Python :: 3
Classifier: License :: OSI Approved :: Apache Software License
Requires-Python: >=3.6
Requires-Dist: omim-data-essential (==10.3.0rc2)
Requires-Dist: omim-data-files (==10.3.0rc2)
Requires-Dist: omim-pygen (==10.3.0rc2)
